cint/__init__.py
cint/cint.py
tests/__init__.py
tests/test_cint.py
cint-1.0.0.dist-info/LICENSE
cint-1.0.0.dist-info/METADATA
cint-1.0.0.dist-info/WHEEL
cint-1.0.0.dist-info/top_level.txt
cint-1.0.0.dist-info/RECORD
