Metadata-Version: 1.2
Name: cint
Version: 1.0.0
Summary: cint - make ctypes great again
Home-page: https://github.com/disconnect3d/cint
Author: disconnect3d
Author-email: dominik.b.czarnota+cint@gmail.com
License: UNKNOWN
Platform: UNKNOWN
Classifier: Development Status :: 5 - Production/Stable
Classifier: License :: OSI Approved :: MIT License
Classifier: Programming Language :: Python :: 2.7
Classifier: Programming Language :: Python :: 3
Requires-Python: >=2.7,!=3.0.*,!=3.1.*,!=3.2.*,!=3.3.*
